CHANGELOG.rst
MANIFEST.in
README.rst
setup.py
slapos/__init__.py
slapos.recipe.build.egg-info/PKG-INFO
slapos.recipe.build.egg-info/SOURCES.txt
slapos.recipe.build.egg-info/dependency_links.txt
slapos.recipe.build.egg-info/entry_points.txt
slapos.recipe.build.egg-info/namespace_packages.txt
slapos.recipe.build.egg-info/requires.txt
slapos.recipe.build.egg-info/top_level.txt
slapos.recipe.build.egg-info/zip-safe
slapos/recipe/__init__.py
slapos/recipe/download.py
slapos/recipe/downloadunpacked.py
slapos/recipe/gitclone.py
slapos/recipe/mkdirectory.py
slapos/recipe/utils.py
slapos/recipe/vm.py
slapos/recipe/build/__init__.py
slapos/recipe/build/tests.py