Metadata-Version: 2.1
Name: slapos.recipe.build
Version: 0.60
Summary: Flexible software building recipe.
Home-page: https://lab.nexedi.com/nexedi/slapos.recipe.build
License: GPLv3
Keywords: slapos recipe
Classifier: Framework :: Buildout :: Recipe
Classifier: Programming Language :: Python
Classifier: Development Status :: 4 - Beta
Classifier: License :: OSI Approved :: GNU General Public License (GPL)
Classifier: Programming Language :: Python :: 2.7
Classifier: Programming Language :: Python :: 3
Classifier: Programming Language :: Python :: 3.7
Classifier: Programming Language :: Python :: 3.8
Classifier: Programming Language :: Python :: 3.9
Classifier: Programming Language :: Python :: 3.10
Classifier: Programming Language :: Python :: 3.11
Classifier: Programming Language :: Python :: 3.12
Requires-Python: >=2.7
Requires-Dist: setuptools
Requires-Dist: zc.buildout
Provides-Extra: test
Requires-Dist: zope.testing; extra == "test"
